simple_fastapi_backend_server/__init__.py
simple_fastapi_backend_server/main.py
simple_fastapi_backend_server-0.1.6.dist-info/METADATA
simple_fastapi_backend_server-0.1.6.dist-info/WHEEL
simple_fastapi_backend_server-0.1.6.dist-info/entry_points.txt
simple_fastapi_backend_server-0.1.6.dist-info/top_level.txt
simple_fastapi_backend_server-0.1.6.dist-info/RECORD
